{
  "name": "1_LLC_BI__EmailTemplate_Institution__c",
  "attributes": [
    "Id",
    "OwnerId",
    "IsDeleted",
    "Name",
    "CreatedDate",
    "CreatedById",
    "LastModifiedDate",
    "LastModifiedById",
    "SystemModstamp",
    "LLC_BI__EmailTemplate__c",
    "LLC_BI__Email_Template_Purpose__c",
    "LLC_BI__Institution__c",
    "LLC_BI__lookupKey__c",
    "AutorabitExtId__c"
  ],
  "records": {
    "1": {
      "AutorabitExtId__c": "",
      "CreatedById": "0055w00000BkiP4AAJ",
      "CreatedDate": "2020-05-14T11:38:20.000Z",
      "Id": "a4o5w000000QJghAAG",
      "IsDeleted": "",
      "LLC_BI__EmailTemplate__c": "00X5w000005zjdz",
      "LLC_BI__Email_Template_Purpose__c": "Account Document Assigned - Bulk",
      "LLC_BI__Institution__c": "a4q5w000000QnPdAAK",
      "LLC_BI__lookupKey__c": "",
      "LastModifiedById": "0055w00000BkiP4AAJ",
      "LastModifiedDate": "2020-05-14T11:38:20.000Z",
      "Name": "ETI-000000054",
      "OwnerId": "0055w00000BkiP4AAJ",
      "SystemModstamp": ""
    },
    "2": {
      "AutorabitExtId__c": "",
      "CreatedById": "0055w00000BkiP4AAJ",
      "CreatedDate": "2020-05-14T11:38:20.000Z",
      "Id": "a4o5w000000QJgiAAG",
      "IsDeleted": "",
      "LLC_BI__EmailTemplate__c": "00X5w000005zje0EAA",
      "LLC_BI__Email_Template_Purpose__c": "Account Document Rejected",
      "LLC_BI__Institution__c": "a4q5w000000QnPdAAK",
      "LLC_BI__lookupKey__c": "",
      "LastModifiedById": "0055w00000BkiP4AAJ",
      "LastModifiedDate": "2020-05-14T11:38:20.000Z",
      "Name": "ETI-000000055",
      "OwnerId": "0055w00000BkiP4AAJ",
      "SystemModstamp": ""
    },
    "3": {
      "AutorabitExtId__c": "",
      "CreatedById": "0055w00000BkiP4AAJ",
      "CreatedDate": "2020-05-14T11:38:20.000Z",
      "Id": "a4o5w000000QJgjAAG",
      "IsDeleted": "",
      "LLC_BI__EmailTemplate__c": "00X5w000005zje1",
      "LLC_BI__Email_Template_Purpose__c": "Borrower Added (Existing)",
      "LLC_BI__Institution__c": "a4q5w000000QnPdAAK",
      "LLC_BI__lookupKey__c": "",
      "LastModifiedById": "0055w00000BkiP4AAJ",
      "LastModifiedDate": "2020-05-14T11:38:20.000Z",
      "Name": "ETI-000000056",
      "OwnerId": "0055w00000BkiP4AAJ",
      "SystemModstamp": ""
    },
    "4": {
      "AutorabitExtId__c": "",
      "CreatedById": "0055w00000BkiP4AAJ",
      "CreatedDate": "2020-05-14T11:38:20.000Z",
      "Id": "a4o5w000000QJgkAAG",
      "IsDeleted": "",
      "LLC_BI__EmailTemplate__c": "00X5w000005zje2",
      "LLC_BI__Email_Template_Purpose__c": "Borrower Added (New)",
      "LLC_BI__Institution__c": "a4q5w000000QnPdAAK",
      "LLC_BI__lookupKey__c": "",
      "LastModifiedById": "0055w00000BkiP4AAJ",
      "LastModifiedDate": "2020-05-14T11:38:20.000Z",
      "Name": "ETI-000000057",
      "OwnerId": "0055w00000BkiP4AAJ",
      "SystemModstamp": ""
    },
    "5": {
      "AutorabitExtId__c": "",
      "CreatedById": "0055w00000BkiP4AAJ",
      "CreatedDate": "2020-05-14T11:38:20.000Z",
      "Id": "a4o5w000000QJglAAG",
      "IsDeleted": "",
      "LLC_BI__EmailTemplate__c": "00X5w000005zje3",
      "LLC_BI__Email_Template_Purpose__c": "Co-Owner Added (Existing)",
      "LLC_BI__Institution__c": "a4q5w000000QnPdAAK",
      "LLC_BI__lookupKey__c": "",
      "LastModifiedById": "0055w00000BkiP4AAJ",
      "LastModifiedDate": "2020-05-14T11:38:20.000Z",
      "Name": "ETI-000000058",
      "OwnerId": "0055w00000BkiP4AAJ",
      "SystemModstamp": ""
    },
    "6": {
      "AutorabitExtId__c": "",
      "CreatedById": "0055w00000BkiP4AAJ",
      "CreatedDate": "2020-05-14T11:38:20.000Z",
      "Id": "a4o5w000000QJgmAAG",
      "IsDeleted": "",
      "LLC_BI__EmailTemplate__c": "00X5w000005zje4",
      "LLC_BI__Email_Template_Purpose__c": "Co-Owner Added (New)",
      "LLC_BI__Institution__c": "a4q5w000000QnPdAAK",
      "LLC_BI__lookupKey__c": "",
      "LastModifiedById": "0055w00000BkiP4AAJ",
      "LastModifiedDate": "2020-05-14T11:38:20.000Z",
      "Name": "ETI-000000059",
      "OwnerId": "0055w00000BkiP4AAJ",
      "SystemModstamp": ""
    },
    "7": {
      "AutorabitExtId__c": "",
      "CreatedById": "0055w00000BkiP4AAJ",
      "CreatedDate": "2020-05-14T11:38:20.000Z",
      "Id": "a4o5w000000QJgnAAG",
      "IsDeleted": "",
      "LLC_BI__EmailTemplate__c": "00X5w000005zje6",
      "LLC_BI__Email_Template_Purpose__c": "Deposit Documents Assigned",
      "LLC_BI__Institution__c": "a4q5w000000QnPdAAK",
      "LLC_BI__lookupKey__c": "",
      "LastModifiedById": "0055w00000BkiP4AAJ",
      "LastModifiedDate": "2020-05-14T11:38:20.000Z",
      "Name": "ETI-000000060",
      "OwnerId": "0055w00000BkiP4AAJ",
      "SystemModstamp": ""
    },
    "8": {
      "AutorabitExtId__c": "",
      "CreatedById": "0055w00000BkiP4AAJ",
      "CreatedDate": "2020-05-14T11:38:20.000Z",
      "Id": "a4o5w000000QJgoAAG",
      "IsDeleted": "",
      "LLC_BI__EmailTemplate__c": "00X5w000005zje5",
      "LLC_BI__Email_Template_Purpose__c": "Deposit Document Rejected",
      "LLC_BI__Institution__c": "a4q5w000000QnPdAAK",
      "LLC_BI__lookupKey__c": "",
      "LastModifiedById": "0055w00000BkiP4AAJ",
      "LastModifiedDate": "2020-05-14T11:38:20.000Z",
      "Name": "ETI-000000061",
      "OwnerId": "0055w00000BkiP4AAJ",
      "SystemModstamp": ""
    },
    "9": {
      "AutorabitExtId__c": "",
      "CreatedById": "0055w00000BkiP4AAJ",
      "CreatedDate": "2020-05-14T11:38:20.000Z",
      "Id": "a4o5w000000QJgpAAG",
      "IsDeleted": "",
      "LLC_BI__EmailTemplate__c": "00X5w000005zjdl",
      "LLC_BI__Email_Template_Purpose__c": "Guarantor Added (Existing)",
      "LLC_BI__Institution__c": "a4q5w000000QnPdAAK",
      "LLC_BI__lookupKey__c": "",
      "LastModifiedById": "0055w00000BkiP4AAJ",
      "LastModifiedDate": "2020-05-14T11:38:20.000Z",
      "Name": "ETI-000000062",
      "OwnerId": "0055w00000BkiP4AAJ",
      "SystemModstamp": ""
    },
    "10": {
      "AutorabitExtId__c": "",
      "CreatedById": "0055w00000BkiP4AAJ",
      "CreatedDate": "2020-05-14T11:38:20.000Z",
      "Id": "a4o5w000000QJgqAAG",
      "IsDeleted": "",
      "LLC_BI__EmailTemplate__c": "00X5w000005zjdm",
      "LLC_BI__Email_Template_Purpose__c": "Guarantor Added (New)",
      "LLC_BI__Institution__c": "a4q5w000000QnPdAAK",
      "LLC_BI__lookupKey__c": "",
      "LastModifiedById": "0055w00000BkiP4AAJ",
      "LastModifiedDate": "2020-05-14T11:38:20.000Z",
      "Name": "ETI-000000063",
      "OwnerId": "0055w00000BkiP4AAJ",
      "SystemModstamp": ""
    },
    "11": {
      "AutorabitExtId__c": "",
      "CreatedById": "0055w00000BkiP4AAJ",
      "CreatedDate": "2020-05-14T11:38:20.000Z",
      "Id": "a4o5w000000QJgrAAG",
      "IsDeleted": "",
      "LLC_BI__EmailTemplate__c": "00X5w000005zjdo",
      "LLC_BI__Email_Template_Purpose__c": "Loan Document Assigned Email - Bulk",
      "LLC_BI__Institution__c": "a4q5w000000QnPdAAK",
      "LLC_BI__lookupKey__c": "",
      "LastModifiedById": "0055w00000BkiP4AAJ",
      "LastModifiedDate": "2020-05-14T11:38:20.000Z",
      "Name": "ETI-000000064",
      "OwnerId": "0055w00000BkiP4AAJ",
      "SystemModstamp": ""
    },
    "12": {
      "AutorabitExtId__c": "",
      "CreatedById": "0055w00000BkiP4AAJ",
      "CreatedDate": "2020-05-14T11:38:20.000Z",
      "Id": "a4o5w000000QJgsAAG",
      "IsDeleted": "",
      "LLC_BI__EmailTemplate__c": "00X5w000005zje7",
      "LLC_BI__Email_Template_Purpose__c": "Loan Document Rejected Email",
      "LLC_BI__Institution__c": "a4q5w000000QnPdAAK",
      "LLC_BI__lookupKey__c": "",
      "LastModifiedById": "0055w00000BkiP4AAJ",
      "LastModifiedDate": "2020-05-14T11:38:20.000Z",
      "Name": "ETI-000000065",
      "OwnerId": "0055w00000BkiP4AAJ",
      "SystemModstamp": ""
    },
    "13": {
      "AutorabitExtId__c": "",
      "CreatedById": "0055w00000BkiP4AAJ",
      "CreatedDate": "2020-05-14T11:38:20.000Z",
      "Id": "a4o5w000000QJgtAAG",
      "IsDeleted": "",
      "LLC_BI__EmailTemplate__c": "00X5w000005zjdv",
      "LLC_BI__Email_Template_Purpose__c": "Save and Continue",
      "LLC_BI__Institution__c": "a4q5w000000QnPdAAK",
      "LLC_BI__lookupKey__c": "",
      "LastModifiedById": "0055w00000BkiP4AAJ",
      "LastModifiedDate": "2020-05-14T11:38:20.000Z",
      "Name": "ETI-000000066",
      "OwnerId": "0055w00000BkiP4AAJ",
      "SystemModstamp": ""
    },
    "14": {
      "AutorabitExtId__c": "",
      "CreatedById": "0055w00000BkiP4AAJ",
      "CreatedDate": "2020-05-14T11:38:20.000Z",
      "Id": "a4o5w000000QJguAAG",
      "IsDeleted": "",
      "LLC_BI__EmailTemplate__c": "00X5w000005zjdz",
      "LLC_BI__Email_Template_Purpose__c": "Account Document Assigned - Bulk",
      "LLC_BI__Institution__c": "a4q5w000000QnPeAAK",
      "LLC_BI__lookupKey__c": "",
      "LastModifiedById": "0055w00000BkiP4AAJ",
      "LastModifiedDate": "2020-05-14T11:38:20.000Z",
      "Name": "ETI-000000067",
      "OwnerId": "0055w00000BkiP4AAJ",
      "SystemModstamp": ""
    },
    "15": {
      "AutorabitExtId__c": "",
      "CreatedById": "0055w00000BkiP4AAJ",
      "CreatedDate": "2020-05-14T11:38:20.000Z",
      "Id": "a4o5w000000QJgvAAG",
      "IsDeleted": "",
      "LLC_BI__EmailTemplate__c": "00X5w000005zje0EAA",
      "LLC_BI__Email_Template_Purpose__c": "Account Document Rejected",
      "LLC_BI__Institution__c": "a4q5w000000QnPeAAK",
      "LLC_BI__lookupKey__c": "",
      "LastModifiedById": "0055w00000BkiP4AAJ",
      "LastModifiedDate": "2020-05-14T11:38:20.000Z",
      "Name": "ETI-000000068",
      "OwnerId": "0055w00000BkiP4AAJ",
      "SystemModstamp": ""
    },
    "16": {
      "AutorabitExtId__c": "",
      "CreatedById": "0055w00000BkiP4AAJ",
      "CreatedDate": "2020-05-14T11:38:20.000Z",
      "Id": "a4o5w000000QJgwAAG",
      "IsDeleted": "",
      "LLC_BI__EmailTemplate__c": "00X5w000005zje1",
      "LLC_BI__Email_Template_Purpose__c": "Borrower Added (Existing)",
      "LLC_BI__Institution__c": "a4q5w000000QnPeAAK",
      "LLC_BI__lookupKey__c": "",
      "LastModifiedById": "0055w00000BkiP4AAJ",
      "LastModifiedDate": "2020-05-14T11:38:20.000Z",
      "Name": "ETI-000000069",
      "OwnerId": "0055w00000BkiP4AAJ",
      "SystemModstamp": ""
    },
    "17": {
      "AutorabitExtId__c": "",
      "CreatedById": "0055w00000BkiP4AAJ",
      "CreatedDate": "2020-05-14T11:38:20.000Z",
      "Id": "a4o5w000000QJgxAAG",
      "IsDeleted": "",
      "LLC_BI__EmailTemplate__c": "00X5w000005zje2",
      "LLC_BI__Email_Template_Purpose__c": "Borrower Added (New)",
      "LLC_BI__Institution__c": "a4q5w000000QnPeAAK",
      "LLC_BI__lookupKey__c": "",
      "LastModifiedById": "0055w00000BkiP4AAJ",
      "LastModifiedDate": "2020-05-14T11:38:20.000Z",
      "Name": "ETI-000000070",
      "OwnerId": "0055w00000BkiP4AAJ",
      "SystemModstamp": ""
    },
    "18": {
      "AutorabitExtId__c": "",
      "CreatedById": "0055w00000BkiP4AAJ",
      "CreatedDate": "2020-05-14T11:38:20.000Z",
      "Id": "a4o5w000000QJgyAAG",
      "IsDeleted": "",
      "LLC_BI__EmailTemplate__c": "00X5w000005zjdl",
      "LLC_BI__Email_Template_Purpose__c": "Co-Owner Added (Existing)",
      "LLC_BI__Institution__c": "a4q5w000000QnPeAAK",
      "LLC_BI__lookupKey__c": "",
      "LastModifiedById": "0055w00000BkiP4AAJ",
      "LastModifiedDate": "2020-05-14T11:38:20.000Z",
      "Name": "ETI-000000071",
      "OwnerId": "0055w00000BkiP4AAJ",
      "SystemModstamp": ""
    },
    "19": {
      "AutorabitExtId__c": "",
      "CreatedById": "0055w00000BkiP4AAJ",
      "CreatedDate": "2020-05-14T11:38:20.000Z",
      "Id": "a4o5w000000QJgzAAG",
      "IsDeleted": "",
      "LLC_BI__EmailTemplate__c": "00X5w000005zjdm",
      "LLC_BI__Email_Template_Purpose__c": "Co-Owner Added (New)",
      "LLC_BI__Institution__c": "a4q5w000000QnPeAAK",
      "LLC_BI__lookupKey__c": "",
      "LastModifiedById": "0055w00000BkiP4AAJ",
      "LastModifiedDate": "2020-05-14T11:38:20.000Z",
      "Name": "ETI-000000072",
      "OwnerId": "0055w00000BkiP4AAJ",
      "SystemModstamp": ""
    },
    "20": {
      "AutorabitExtId__c": "",
      "CreatedById": "0055w00000BkiP4AAJ",
      "CreatedDate": "2020-05-14T11:38:20.000Z",
      "Id": "a4o5w000000QJh0AAG",
      "IsDeleted": "",
      "LLC_BI__EmailTemplate__c": "00X5w000005zje6",
      "LLC_BI__Email_Template_Purpose__c": "Deposit Documents Assigned",
      "LLC_BI__Institution__c": "a4q5w000000QnPeAAK",
      "LLC_BI__lookupKey__c": "",
      "LastModifiedById": "0055w00000BkiP4AAJ",
      "LastModifiedDate": "2020-05-14T11:38:20.000Z",
      "Name": "ETI-000000073",
      "OwnerId": "0055w00000BkiP4AAJ",
      "SystemModstamp": ""
    },
    "21": {
      "AutorabitExtId__c": "",
      "CreatedById": "0055w00000BkiP4AAJ",
      "CreatedDate": "2020-05-14T11:38:20.000Z",
      "Id": "a4o5w000000QJh1AAG",
      "IsDeleted": "",
      "LLC_BI__EmailTemplate__c": "00X5w000005zje5",
      "LLC_BI__Email_Template_Purpose__c": "Deposit Document Rejected",
      "LLC_BI__Institution__c": "a4q5w000000QnPeAAK",
      "LLC_BI__lookupKey__c": "",
      "LastModifiedById": "0055w00000BkiP4AAJ",
      "LastModifiedDate": "2020-05-14T11:38:20.000Z",
      "Name": "ETI-000000074",
      "OwnerId": "0055w00000BkiP4AAJ",
      "SystemModstamp": ""
    },
    "22": {
      "AutorabitExtId__c": "",
      "CreatedById": "0055w00000BkiP4AAJ",
      "CreatedDate": "2020-05-14T11:38:20.000Z",
      "Id": "a4o5w000000QJh2AAG",
      "IsDeleted": "",
      "LLC_BI__EmailTemplate__c": "00X5w000005zje3",
      "LLC_BI__Email_Template_Purpose__c": "Guarantor Added (Existing)",
      "LLC_BI__Institution__c": "a4q5w000000QnPeAAK",
      "LLC_BI__lookupKey__c": "",
      "LastModifiedById": "0055w00000BkiP4AAJ",
      "LastModifiedDate": "2020-05-14T11:38:20.000Z",
      "Name": "ETI-000000075",
      "OwnerId": "0055w00000BkiP4AAJ",
      "SystemModstamp": ""
    },
    "23": {
      "AutorabitExtId__c": "",
      "CreatedById": "0055w00000BkiP4AAJ",
      "CreatedDate": "2020-05-14T11:38:20.000Z",
      "Id": "a4o5w000000QJh3AAG",
      "IsDeleted": "",
      "LLC_BI__EmailTemplate__c": "00X5w000005zje4",
      "LLC_BI__Email_Template_Purpose__c": "Guarantor Added (New)",
      "LLC_BI__Institution__c": "a4q5w000000QnPeAAK",
      "LLC_BI__lookupKey__c": "",
      "LastModifiedById": "0055w00000BkiP4AAJ",
      "LastModifiedDate": "2020-05-14T11:38:20.000Z",
      "Name": "ETI-000000076",
      "OwnerId": "0055w00000BkiP4AAJ",
      "SystemModstamp": ""
    },
    "24": {
      "AutorabitExtId__c": "",
      "CreatedById": "0055w00000BkiP4AAJ",
      "CreatedDate": "2020-05-14T11:38:20.000Z",
      "Id": "a4o5w000000QJh4AAG",
      "IsDeleted": "",
      "LLC_BI__EmailTemplate__c": "00X5w000005zjdo",
      "LLC_BI__Email_Template_Purpose__c": "Loan Document Assigned Email - Bulk",
      "LLC_BI__Institution__c": "a4q5w000000QnPeAAK",
      "LLC_BI__lookupKey__c": "",
      "LastModifiedById": "0055w00000BkiP4AAJ",
      "LastModifiedDate": "2020-05-14T11:38:20.000Z",
      "Name": "ETI-000000077",
      "OwnerId": "0055w00000BkiP4AAJ",
      "SystemModstamp": ""
    },
    "25": {
      "AutorabitExtId__c": "",
      "CreatedById": "0055w00000BkiP4AAJ",
      "CreatedDate": "2020-05-14T11:38:20.000Z",
      "Id": "a4o5w000000QJh5AAG",
      "IsDeleted": "",
      "LLC_BI__EmailTemplate__c": "00X5w000005zje7",
      "LLC_BI__Email_Template_Purpose__c": "Loan Document Rejected Email",
      "LLC_BI__Institution__c": "a4q5w000000QnPeAAK",
      "LLC_BI__lookupKey__c": "",
      "LastModifiedById": "0055w00000BkiP4AAJ",
      "LastModifiedDate": "2020-05-14T11:38:20.000Z",
      "Name": "ETI-000000078",
      "OwnerId": "0055w00000BkiP4AAJ",
      "SystemModstamp": ""
    },
    "26": {
      "AutorabitExtId__c": "",
      "CreatedById": "0055w00000BkiP4AAJ",
      "CreatedDate": "2020-05-14T11:38:20.000Z",
      "Id": "a4o5w000000QJh6AAG",
      "IsDeleted": "",
      "LLC_BI__EmailTemplate__c": "00X5w000005zjdv",
      "LLC_BI__Email_Template_Purpose__c": "Save and Continue",
      "LLC_BI__Institution__c": "a4q5w000000QnPeAAK",
      "LLC_BI__lookupKey__c": "",
      "LastModifiedById": "0055w00000BkiP4AAJ",
      "LastModifiedDate": "2020-05-14T11:38:20.000Z",
      "Name": "ETI-000000079",
      "OwnerId": "0055w00000BkiP4AAJ",
      "SystemModstamp": ""
    },
    "27": {
      "AutorabitExtId__c": "",
      "CreatedById": "0055w00000BkiP4AAJ",
      "CreatedDate": "2020-05-14T11:38:20.000Z",
      "Id": "a4o5w000000QJh8AAG",
      "IsDeleted": "",
      "LLC_BI__EmailTemplate__c": "00X5w000005zjdd",
      "LLC_BI__Email_Template_Purpose__c": "",
      "LLC_BI__Institution__c": "a4q5w000000QnPeAAK",
      "LLC_BI__lookupKey__c": "dth56htrshrgerrh5",
      "LastModifiedById": "0055w00000BkiP4AAJ",
      "LastModifiedDate": "2020-05-14T11:38:20.000Z",
      "Name": "ETI-000000081",
      "OwnerId": "0055w00000BkiP4AAJ",
      "SystemModstamp": ""
    },
    "28": {
      "AutorabitExtId__c": "a4o4T000000PEz5QAG",
      "CreatedById": "0055w00000BkiP4AAJ",
      "CreatedDate": "2020-05-14T11:38:20.000Z",
      "Id": "a4o5w000000QJh7AAG",
      "IsDeleted": "",
      "LLC_BI__EmailTemplate__c": "00X5w000005zjde",
      "LLC_BI__Email_Template_Purpose__c": "",
      "LLC_BI__Institution__c": "a4q5w000000QnPdAAK",
      "LLC_BI__lookupKey__c": "dth56htrshrh5",
      "LastModifiedById": "0055w00000BkiP4AAJ",
      "LastModifiedDate": "2020-11-30T16:59:17.000Z",
      "Name": "ETI-000000080",
      "OwnerId": "0055w00000BkiP4AAJ",
      "SystemModstamp": ""
    }
  }
}