{
  "name": "1_nFORCE__Screen__c",
  "attributes": [
    "Id",
    "OwnerId",
    "IsDeleted",
    "Name",
    "CreatedDate",
    "CreatedById",
    "LastModifiedDate",
    "LastModifiedById",
    "SystemModstamp",
    "LastActivityDate",
    "nFORCE__Disable_Print__c",
    "nFORCE__Show_Link_To_Context_Object__c",
    "nFORCE__lookupKey__c",
    "AutorabitExtId__c"
  ],
  "records": {
    "1": {
      "AutorabitExtId__c": "",
      "CreatedById": "0055w00000BkiP4AAJ",
      "CreatedDate": "2020-05-14T11:38:20.000Z",
      "Id": "a345w0000036vjsAAA",
      "IsDeleted": "",
      "LastActivityDate": "",
      "LastModifiedById": "0055w00000BkiP4AAJ",
      "LastModifiedDate": "2020-05-14T11:38:20.000Z",
      "Name": "Online Banking",
      "OwnerId": "0055w00000BkiP4AAJ",
      "SystemModstamp": "",
      "nFORCE__Disable_Print__c": "false",
      "nFORCE__Show_Link_To_Context_Object__c": "true",
      "nFORCE__lookupKey__c": ""
    },
    "2": {
      "AutorabitExtId__c": "",
      "CreatedById": "0055w00000BkiP4AAJ",
      "CreatedDate": "2020-05-14T11:38:20.000Z",
      "Id": "a345w0000036vjtAAA",
      "IsDeleted": "",
      "LastActivityDate": "",
      "LastModifiedById": "0055w00000BkiP4AAJ",
      "LastModifiedDate": "2020-05-14T11:38:20.000Z",
      "Name": "Overdraft Protection",
      "OwnerId": "0055w00000BkiP4AAJ",
      "SystemModstamp": "",
      "nFORCE__Disable_Print__c": "false",
      "nFORCE__Show_Link_To_Context_Object__c": "true",
      "nFORCE__lookupKey__c": ""
    },
    "3": {
      "AutorabitExtId__c": "a345w0000036vjuAAA",
      "CreatedById": "0055w00000Cu9fGAAR",
      "CreatedDate": "2020-05-14T11:38:20.000Z",
      "Id": "a345w0000036vjuAAA",
      "IsDeleted": "",
      "LastActivityDate": "",
      "LastModifiedById": "0055w00000BkiP4AAJ",
      "LastModifiedDate": "2021-01-28T16:48:56.000Z",
      "Name": "Default Loan Facility Creation Fields",
      "OwnerId": "0055w00000BkiP4AAJ",
      "SystemModstamp": "",
      "nFORCE__Disable_Print__c": "false",
      "nFORCE__Show_Link_To_Context_Object__c": "true",
      "nFORCE__lookupKey__c": "42280894319758149"
    },
    "4": {
      "AutorabitExtId__c": "",
      "CreatedById": "0055w00000BkiP4AAJ",
      "CreatedDate": "2020-05-14T11:38:20.000Z",
      "Id": "a345w0000036vjwAAA",
      "IsDeleted": "",
      "LastActivityDate": "",
      "LastModifiedById": "0055w00000BkiP4AAJ",
      "LastModifiedDate": "2020-05-14T11:38:20.000Z",
      "Name": "Product Package Credit Memo",
      "OwnerId": "0055w00000BkiP4AAJ",
      "SystemModstamp": "",
      "nFORCE__Disable_Print__c": "false",
      "nFORCE__Show_Link_To_Context_Object__c": "true",
      "nFORCE__lookupKey__c": "42927115042672124"
    }
  }
}